gsc_events/__init__.py
gsc_events/client.py
gsc_events/core/__init__.py
gsc_events/core/events.py
gsc_events/core/watcher.py
gsc_events-0.1.4.dist-info/licenses/LICENSE
gsc_events-0.1.4.dist-info/METADATA
gsc_events-0.1.4.dist-info/WHEEL
gsc_events-0.1.4.dist-info/top_level.txt
gsc_events-0.1.4.dist-info/RECORD
