Metadata-Version: 2.4
Name: gsc_events
Version: 0.1.4
Summary: Python library for capturing and handling game events in Plutonium T6
Home-page: https://github.com/Yallamaztar/gsc-events
Author: budiworld
Author-email: budi.world@yahoo.com
Classifier: Programming Language :: Python :: 3
Classifier: License :: OSI Approved :: MIT License
Classifier: Operating System :: OS Independent
Requires-Python: >=3.13
License-File: LICENSE
Dynamic: author
Dynamic: author-email
Dynamic: classifier
Dynamic: description
Dynamic: description-content-type
Dynamic: home-page
Dynamic: license-file
Dynamic: requires-python
Dynamic: summary
